pistol_magazine/__init__.py
pistol_magazine/base.py
pistol_magazine/bool.py
pistol_magazine/cli.py
pistol_magazine/datetime.py
pistol_magazine/dict.py
pistol_magazine/float.py
pistol_magazine/int.py
pistol_magazine/list.py
pistol_magazine/provider.py
pistol_magazine/self_made.py
pistol_magazine/str.py
pistol_magazine/timestamp.py
pistol_magazine/built_in_provider/__init__.py
pistol_magazine/built_in_provider/cyclic_parameter.py
pistol_magazine/built_in_provider/fixed_value.py
pistol_magazine/built_in_provider/incremental_value.py
pistol_magazine/built_in_provider/random_choice_from_list.py
pistol_magazine/built_in_provider/random_float_in_range.py
pistol_magazine/built_in_provider/regex.py
pistol_magazine/data_exporter/__init__.py
pistol_magazine/data_exporter/csv_ex.py
pistol_magazine/data_exporter/db_ex.py
pistol_magazine/data_exporter/exporter.py
pistol_magazine/data_exporter/json_ex.py
pistol_magazine/data_exporter/xml_ex.py
pistol_magazine/data_exporter/yaml_ex.py
pistol_magazine/hooks/__init__.py
pistol_magazine/hooks/hook_manager.py
pistol_magazine/hooks/hooks.py
tests/__init__.py
tests/regular_temp.py
tests/test_bool.py
tests/test_data_export.py
tests/test_datetime.py
tests/test_dict.py
tests/test_fake_max_push_data.py
tests/test_float.py
tests/test_int.py
tests/test_list.py
tests/test_postman_RESTful_API.py
tests/test_research.py
tests/test_selfmade.py
tests/test_str.py
tests/test_timestamp.py
PistolMagazine-0.8.5.dist-info/LICENSE
PistolMagazine-0.8.5.dist-info/METADATA
PistolMagazine-0.8.5.dist-info/WHEEL
PistolMagazine-0.8.5.dist-info/entry_points.txt
PistolMagazine-0.8.5.dist-info/top_level.txt
PistolMagazine-0.8.5.dist-info/RECORD
