Metadata-Version: 2.1
Name: PistolMagazine
Version: 0.8.5
Summary: A data mocking tool designed to help you generate realistic data for testing and development purposes.
Home-page: https://github.com/yourusername/your-repo
Author: Ealyn
Author-email: miyuk1@126.com
Classifier: Programming Language :: Python :: 3
Classifier: License :: OSI Approved :: MIT License
Classifier: Operating System :: OS Independent
Requires-Python: >=3.6
License-File: LICENSE
Requires-Dist: Faker ==25.1.0
Requires-Dist: dicttoxml ~=1.7.16
Requires-Dist: PyMySQL ~=1.0.2
Requires-Dist: rstr ~=3.2.2
Requires-Dist: click ~=8.0.3
